ccsgp_get_started/__init__.py
ccsgp_get_started/__main__.py
ccsgp_get_started/ccsgp/__init__.py
ccsgp_get_started/ccsgp/ccsgp.py
ccsgp_get_started/ccsgp/config.py
ccsgp_get_started/ccsgp/myplot.py
ccsgp_get_started/ccsgp/utils.py
ccsgp_get_started/ccsgp/Gnuplot/__init__.py
ccsgp_get_started/ccsgp/Gnuplot/_Gnuplot.py
ccsgp_get_started/ccsgp/Gnuplot/demo.py
ccsgp_get_started/ccsgp/Gnuplot/Errors.py
ccsgp_get_started/ccsgp/Gnuplot/funcutils.py
ccsgp_get_started/ccsgp/Gnuplot/gnuplot_Suites.py
ccsgp_get_started/ccsgp/Gnuplot/gp.py
ccsgp_get_started/ccsgp/Gnuplot/gp_cygwin.py
ccsgp_get_started/ccsgp/Gnuplot/gp_java.py
ccsgp_get_started/ccsgp/Gnuplot/gp_mac.py
ccsgp_get_started/ccsgp/Gnuplot/gp_macosx.py
ccsgp_get_started/ccsgp/Gnuplot/gp_unix.py
ccsgp_get_started/ccsgp/Gnuplot/gp_win32.py
ccsgp_get_started/ccsgp/Gnuplot/PlotItems.py
ccsgp_get_started/ccsgp/Gnuplot/setup.py
ccsgp_get_started/ccsgp/Gnuplot/termdefs.py
ccsgp_get_started/ccsgp/Gnuplot/test.py
ccsgp_get_started/ccsgp/Gnuplot/utils.py
ccsgp_get_started/examples/__init__.py
ccsgp_get_started/examples/gp_background.py
ccsgp_get_started/examples/gp_ccX.py
ccsgp_get_started/examples/gp_datdir.py
ccsgp_get_started/examples/gp_effcorr.py
ccsgp_get_started/examples/gp_lcltpt.py
ccsgp_get_started/examples/gp_panel.py
ccsgp_get_started/examples/gp_ptspec.py
ccsgp_get_started/examples/gp_purity.py
ccsgp_get_started/examples/gp_rapp.py
ccsgp_get_started/examples/gp_rdiff.py
ccsgp_get_started/examples/gp_sims.py
ccsgp_get_started/examples/gp_stack.py
ccsgp_get_started/examples/gp_tbw.py
ccsgp_get_started/examples/gp_xfac.py
ccsgp_get_started/examples/utils.py
ccsgp_get_started-2.1.0.dist-info/DESCRIPTION.rst
ccsgp_get_started-2.1.0.dist-info/METADATA
ccsgp_get_started-2.1.0.dist-info/metadata.json
ccsgp_get_started-2.1.0.dist-info/pbr.json
ccsgp_get_started-2.1.0.dist-info/RECORD
ccsgp_get_started-2.1.0.dist-info/top_level.txt
ccsgp_get_started-2.1.0.dist-info/WHEEL
