Metadata-Version: 2.0
Name: ccsgp-get-started
Version: 2.1.0
Summary: get started with the ccsgp plotting library
Home-page: https://github.com/tschaume/ccsgp_get_started
Author: Patrick Huck
Author-email: patrick@the-huck.com
License: MIT
Keywords: gnuplot,graph,plot,panel
Platform: UNKNOWN
Requires-Dist: numpy (==1.9.2)
Requires-Dist: Pint (==0.5.1)
Requires-Dist: uncertainties (==2.4.4)
